{
  "content": "Passenger who died on cruise ship was served 33 drinks, lawsuit alleges Telehealth weight-loss drug scam hits customers as FTC issues major warning Solar eruption is expected to hit Earth and may cause some tech disruptions Some teens are 1 step ahead as world-1st social media ban takes effect in Australia A growing number of shoppers are stealing from self-checkout, survey finds Stories for you - BusinessYahoo Personal Finance Here's why you should open a CD account before the Fed's next meeting Fed rate cuts cause CD rates to fall. So, with the next Fed meeting coming up and a rate cut likely now is a good time to open a CD and lock in today's high rates. - USCBS News Grammy-nominated musician killed by driver with over 100 arrests Roderick Macleod, 70, was walking his dogs when he was allegedly struck by a driver with dozens of prior arrests. - USWFTV Sonic boom advisory issued ahead of Falcon 9 rocket launch Tuesday from Florida People in Central Florida could hear a distant boom Tuesday afternoon. - - USAssociated Press Florida governor declares Muslim civil rights group a terrorist organization Florida Gov. Ron DeSantis on Monday designated one of the largest Muslim civil rights and advocacy groups in the U.S. a foreign terrorist organization, following a similar step by Texas last month. The directive against the Council on American-Islamic Relations comes in an executive order DeSantis posted on the social media site X. It also gives the same label to the Muslim Brotherhood. Neither CAIR nor the Muslim Brotherhood is designated as a foreign terrorist organization by the U.S. gove - USThe Daily Beast Hot Mic at ICE Barbie Event Catches TSA Agents Admitting Theyre Terrified A hot mic before Homeland Security Secretary Kristi Noems Monday press conference picked up an unexpectedly candid glimpse into how some TSA agents actually feel about their jobs. The audio captured one of the agents complaining about being scared of his superior before the event at Tampa International Airport in Florida, where Noem presented over a dozen TSA agents with $10,000 bonus checks for working without pay during the government shutdown. I used to be terrified of [her] when I starte - BusinessGuruFocus.com Ray-Ban Meta Glasses Gain Momentum but Face Privacy and Competition Challenges Early sales strength tested as regulators and rivals intensify pressure - PoliticsYahoo Finance Trump tariffs live updates: Trump floats 'some' additional tariff carveouts; US unveils $12B farmer bailout Yahoo Finance is chronicling the latest news and updates on President Trump's plans to impose tariffs on goods from other countries.",
  "error": null,
  "hashes": {
    "content_hash": "7c553af8cddc043a",
    "url_hash": "a25d22ea4abb7479"
  },
  "method": "trafilatura",
  "success": true,
  "timestamps": {
    "access_count": 1,
    "cached_at": 1765305587.3145976,
    "expires_at": 1765910387.3145976,
    "fetched_at": 1765305587.3145976,
    "last_accessed": 1765305587.3145976
  },
  "title": "Yahoo News: Latest and Breaking News, Headlines, Live Updates, and More",
  "url": "https://news.yahoo.com/"
}